lts_workflows_sm_scrnaseq/__init__.py
lts_workflows_sm_scrnaseq/_version.py
lts_workflows_sm_scrnaseq/environment-27.yaml
lts_workflows_sm_scrnaseq/environment.yaml
lts_workflows_sm_scrnaseq/workflow.sm
lts_workflows_sm_scrnaseq/rules/main.settings
lts_workflows_sm_scrnaseq/rules/ngs.settings
lts_workflows_sm_scrnaseq/rules/bamtools/bamtools.settings
lts_workflows_sm_scrnaseq/rules/bamtools/bamtools_create_filter_script.rule
lts_workflows_sm_scrnaseq/rules/bamtools/bamtools_filter.rule
lts_workflows_sm_scrnaseq/rules/bamtools/bamtools_filter_script.rule
lts_workflows_sm_scrnaseq/rules/bamtools/bamtools_filter_unique.rule
lts_workflows_sm_scrnaseq/rules/bamtools/env.yaml
lts_workflows_sm_scrnaseq/rules/bedtools/bedtools.settings
lts_workflows_sm_scrnaseq/rules/bedtools/bedtools_bamtobed.rule
lts_workflows_sm_scrnaseq/rules/bedtools/env.yaml
lts_workflows_sm_scrnaseq/rules/comp/comp.settings
lts_workflows_sm_scrnaseq/rules/ercc/ercc.settings
lts_workflows_sm_scrnaseq/rules/ercc/ercc_create_ref.rule
lts_workflows_sm_scrnaseq/rules/ercc/ercc_download_metadata.rule
lts_workflows_sm_scrnaseq/rules/picard/env.yaml
lts_workflows_sm_scrnaseq/rules/picard/picard.settings
lts_workflows_sm_scrnaseq/rules/picard/picard_merge_sam.rule
lts_workflows_sm_scrnaseq/rules/picard/picard_sort_sam.rule
lts_workflows_sm_scrnaseq/rules/rpkmforgenes/env.yaml
lts_workflows_sm_scrnaseq/rules/rpkmforgenes/rpkmforgenes.settings
lts_workflows_sm_scrnaseq/rules/rpkmforgenes/rpkmforgenes_from_bam.rule
lts_workflows_sm_scrnaseq/rules/rsem/env.yaml
lts_workflows_sm_scrnaseq/rules/rsem/rsem.settings
lts_workflows_sm_scrnaseq/rules/rsem/rsem_calculate_expression.rule
lts_workflows_sm_scrnaseq/rules/rsem/rsem_prepare_reference.rule
lts_workflows_sm_scrnaseq/rules/rseqc/env.yaml
lts_workflows_sm_scrnaseq/rules/rseqc/rseqc.settings
lts_workflows_sm_scrnaseq/rules/rseqc/rseqc_clipping_profile.rule
lts_workflows_sm_scrnaseq/rules/rseqc/rseqc_geneBody_coverage.rule
lts_workflows_sm_scrnaseq-0.1.0.dist-info/DESCRIPTION.rst
lts_workflows_sm_scrnaseq-0.1.0.dist-info/METADATA
lts_workflows_sm_scrnaseq-0.1.0.dist-info/RECORD
lts_workflows_sm_scrnaseq-0.1.0.dist-info/WHEEL
lts_workflows_sm_scrnaseq-0.1.0.dist-info/metadata.json
lts_workflows_sm_scrnaseq-0.1.0.dist-info/top_level.txt
