Metadata-Version: 2.0
Name: lts-workflows-sm-scrnaseq
Version: 0.1.0
Summary: single-cell RNA sequencing snakemake workflow
Home-page: UNKNOWN
Author: Per Unneberg
Author-email: per.unneberg@scilifelab.se
License: GNU General Public License v3
Keywords: lts_workflows_sm_scrnaseq
Platform: UNKNOWN
Classifier: Development Status :: 2 - Pre-Alpha
Classifier: Intended Audience :: Developers
Classifier: License :: OSI Approved :: GNU General Public License v3 (GPLv3)
Classifier: Natural Language :: English
Classifier: Programming Language :: Python :: 3.3
Classifier: Programming Language :: Python :: 3.4
Classifier: Programming Language :: Python :: 3.5
Requires-Dist: lts-workflows
Requires-Dist: pyyaml (>=3.11)
